tortoise3/__init__.py
tortoise3/backends/__init__.py
tortoise3/backends/asyncpg/__init__.py
tortoise3/backends/asyncpg/client.py
tortoise3/backends/asyncpg/executor.py
tortoise3/backends/asyncpg/schema_generator.py
tortoise3/backends/base/__init__.py
tortoise3/backends/base/client.py
tortoise3/backends/base/config_generator.py
tortoise3/backends/base/executor.py
tortoise3/backends/base/schema_generator.py
tortoise3/backends/base_postgres/__init__.py
tortoise3/backends/base_postgres/client.py
tortoise3/backends/base_postgres/executor.py
tortoise3/backends/base_postgres/schema_generator.py
tortoise3/backends/mssql/__init__.py
tortoise3/backends/mssql/client.py
tortoise3/backends/mssql/executor.py
tortoise3/backends/mssql/schema_generator.py
tortoise3/backends/mysql/__init__.py
tortoise3/backends/mysql/client.py
tortoise3/backends/mysql/executor.py
tortoise3/backends/mysql/schema_generator.py
tortoise3/backends/odbc/__init__.py
tortoise3/backends/odbc/client.py
tortoise3/backends/odbc/executor.py
tortoise3/backends/oracle/__init__.py
tortoise3/backends/oracle/client.py
tortoise3/backends/oracle/executor.py
tortoise3/backends/oracle/schema_generator.py
tortoise3/backends/psycopg/__init__.py
tortoise3/backends/psycopg/client.py
tortoise3/backends/psycopg/executor.py
tortoise3/backends/psycopg/schema_generator.py
tortoise3/backends/sqlite/__init__.py
tortoise3/backends/sqlite/client.py
tortoise3/backends/sqlite/executor.py
tortoise3/backends/sqlite/schema_generator.py
tortoise3/connection.py
tortoise3/contrib/__init__.py
tortoise3/contrib/aiohttp/__init__.py
tortoise3/contrib/blacksheep/__init__.py
tortoise3/contrib/fastapi/__init__.py
tortoise3/contrib/mysql/__init__.py
tortoise3/contrib/mysql/fields.py
tortoise3/contrib/mysql/functions.py
tortoise3/contrib/mysql/indexes.py
tortoise3/contrib/mysql/json_functions.py
tortoise3/contrib/mysql/search.py
tortoise3/contrib/postgres/__init__.py
tortoise3/contrib/postgres/fields.py
tortoise3/contrib/postgres/functions.py
tortoise3-0.1.1.dist-info/LICENSE
tortoise3-0.1.1.dist-info/METADATA
tortoise3-0.1.1.dist-info/WHEEL
tortoise3-0.1.1.dist-info/RECORD
