Metadata-Version: 2.1
Name: tortoise3
Version: 0.1.1
Summary: tortoise-orm的国产化替代版本
Home-page: https://gitee.com/zhangdapeng520/tortoise3
License: Apache-2.0
Author: 张大鹏
Author-email: 1156956636@qq.com
Requires-Python: >=3.12,<4.0
Classifier: License :: OSI Approved :: Apache Software License
Classifier: Programming Language :: Python :: 3
Classifier: Programming Language :: Python :: 3.12
Classifier: Programming Language :: Python :: 3.13
Requires-Dist: aiomysql
Requires-Dist: aiosqlite (>=0.16.0,<0.18.0)
Requires-Dist: asyncmy (>=0.2.8,<0.3.0)
Requires-Dist: asyncodbc (>=0.1.1,<0.2.0)
Requires-Dist: asyncpg
Requires-Dist: ciso8601 ; sys_platform != "win32" and implementation_name == "cpython"
Requires-Dist: iso8601 (>=1.0.2,<2.0.0)
Requires-Dist: orjson
Requires-Dist: psycopg[binary,pool] (>=3.0.12,<4.0.0)
Requires-Dist: pydantic (>=2.0,<3.0,!=2.7.0)
Requires-Dist: pytz
Requires-Dist: uvloop ; sys_platform != "win32" and implementation_name == "cpython"
Project-URL: Repository, https://gitee.com/zhangdapeng520/tortoise3.git
